surface_erode/Makefile
surface_erode/__init__.py
surface_erode/src/surfaceErode.cu
surface_erode-0.1.0.dist-info/WHEEL
surface_erode-0.1.0.dist-info/METADATA
surface_erode-0.1.0.dist-info/RECORD
